openapi_bridge/__init__.py
openapi_bridge-0.5.0.dist-info/LICENSE
openapi_bridge-0.5.0.dist-info/METADATA
openapi_bridge-0.5.0.dist-info/WHEEL
openapi_bridge-0.5.0.dist-info/RECORD
