Metadata-Version: 2.1
Name: openapi-bridge
Version: 0.5.0
Summary: 
Home-page: https://github.com/solute/openapi-bridge
License: Apache-2.0
Author: Patrick Schemitz
Author-email: ps@solute.de
Requires-Python: >=3.9,<4.0
Classifier: License :: OSI Approved :: Apache Software License
Classifier: Programming Language :: Python :: 3
Classifier: Programming Language :: Python :: 3.9
Classifier: Programming Language :: Python :: 3.10
Classifier: Programming Language :: Python :: 3.11
Classifier: Programming Language :: Python :: 3.12
Classifier: Programming Language :: Python :: 3.13
Requires-Dist: pydantic (>=2.1.1,<3.0.0)
Project-URL: Repository, https://github.com/solute/openapi-bridge
